[
  {
    "topic": "Chapter 9. THE HUMAN RIGHTS ACT OF 1998",
    "href": "chapter-1.xhtml",
    "order": 0
  },
  {
    "topic": "The Dynamic Relationship between the European Convention on Human Rights and the Human Rights Act 1998",
    "href": "chapter-1.xhtml#chapter-1-4",
    "order": 1
  },
  {
    "topic": "Dissecting HRA Section 1—the Incorporation of the Convention’s Rights into Domestic Law",
    "href": "chapter-1.xhtml#chapter-1-14",
    "order": 2
  },
  {
    "topic": "The Role of Section 2 of the HRA in Interpreting Convention Rights",
    "href": "chapter-1.xhtml#chapter-1-139",
    "order": 3
  },
  {
    "topic": "The HRA's Section 3 and Its Impact on Legislation Interpretation",
    "href": "chapter-1.xhtml#chapter-1-147",
    "order": 4
  },
  {
    "topic": "Section 4 and Declarations of Incompatibility",
    "href": "chapter-1.xhtml#chapter-1-160",
    "order": 5
  },
  {
    "topic": "Section 6 and Its Enforcement Against Public Authorities",
    "href": "chapter-1.xhtml#chapter-1-185",
    "order": 6
  },
  {
    "topic": "Section 7 and Legal Proceedings Against Public Authorities",
    "href": "chapter-1.xhtml#chapter-1-210",
    "order": 7
  },
  {
    "topic": "Section 8 and Available Remedies",
    "href": "chapter-1.xhtml#chapter-1-226",
    "order": 8
  },
  {
    "topic": "Combating Discrimination Through the ECHR and the Equality Act 2010",
    "href": "chapter-1.xhtml#chapter-1-241",
    "order": 9
  },
  {
    "topic": "Chapter 10. Law on Public Order",
    "href": "chapter-2.xhtml",
    "order": 10
  },
  {
    "topic": "The Interplay between ECHR and HRA",
    "href": "chapter-2.xhtml#chapter-2-283",
    "order": 11
  },
  {
    "topic": "Breach of the Peace",
    "href": "chapter-2.xhtml#chapter-2-299",
    "order": 12
  },
  {
    "topic": "Regulation of Public Processions",
    "href": "chapter-2.xhtml#chapter-2-352",
    "order": 13
  },
  {
    "topic": "Regulation of Public Assemblies",
    "href": "chapter-2.xhtml#chapter-2-411",
    "order": 14
  }
]